[
  {
    "slug": "eigenmietwert-imputed-rental-value-switzerland-complete-guide",
    "title": "Eigenmietwert Explained: The Complete Guide to Imputed Rental Value in Switzerland",
    "date": "2026-02-01",
    "category": "Real Estate",
    "readTime": "12 min read"
  },
  {
    "slug": "swiss-tax-return-guide-2025-complete-step-by-step-tutorial",
    "title": "Swiss Tax Return Guide 2025: Complete Step-by-Step Tutorial",
    "date": "2025-11-28",
    "category": "Tax Basics",
    "readTime": "18 min read"
  },
  {
    "slug": "top-10-tax-deductions-expats-switzerland-2025",
    "title": "Top 10 Tax Deductions for Expats in Switzerland 2025",
    "date": "2025-11-27",
    "category": "Tax Deductions",
    "readTime": "14 min read"
  },
  {
    "slug": "swiss-kita-costs-tax-deductions-guide-parents-2025",
    "title": "Swiss Kita Costs and Tax Deductions: Complete Guide for Parents 2025",
    "date": "2025-02-03",
    "category": "Family & Children",
    "readTime": "12 min read"
  },
  {
    "slug": "swiss-agricultural-tariffs-usa-trade-negotiations-2025",
    "title": "Swiss Agricultural Tariffs: Can Switzerland Reduce Tariffs for Better USA Trade Deal?",
    "date": "2025-02-02",
    "category": "International Trade",
    "readTime": "10 min read"
  },
  {
    "slug": "switzerland-usa-fatca-agreement-tax-dispute-resolution-2013",
    "title": "Switzerland-USA FATCA Agreement: How the Tax Dispute Was Resolved in 2013",
    "date": "2025-02-01",
    "category": "International Tax",
    "readTime": "12 min read"
  },
  {
    "slug": "swiss-eigenmietwert-referendum-property-tax-changes-2025",
    "title": "Swiss Eigenmietwert Referendum Approved: What the Property Tax Reform Means for You",
    "date": "2025-01-30",
    "category": "Real Estate",
    "readTime": "15 min read"
  },
  {
    "slug": "retroactive-pillar-3a-contributions-switzerland-2025",
    "title": "Retroactive Pillar 3a Contributions: New Opportunities for Swiss Retirement Planning 2025",
    "date": "2025-01-25",
    "category": "Pension & Savings",
    "readTime": "10 min read"
  },
  {
    "slug": "tax-deductible-expenses-switzerland-2025-guide-individuals",
    "title": "Tax-Deductible Expenses in Switzerland: 2025 Guide for Individuals",
    "date": "2025-01-20",
    "category": "Tax Deductions",
    "readTime": "12 min read"
  },
  {
    "slug": "flexible-retirement-switzerland-tax-implications-2025",
    "title": "Flexible Retirement in Switzerland: Tax Implications and Planning Strategies 2025",
    "date": "2025-01-20",
    "category": "Pension & Savings",
    "readTime": "12 min read"
  },
  {
    "slug": "swiss-tax-developments-2025-oecd-minimum-tax-implementation",
    "title": "Swiss Tax Developments 2025: OECD Minimum Tax Implementation and Corporate Tax Reforms",
    "date": "2025-01-20",
    "category": "Corporate Tax",
    "readTime": "15 min read"
  },
  {
    "slug": "understanding-swiss-tax-at-source-quellensteuer-2025",
    "title": "Understanding Swiss Tax at Source (Quellensteuer) in 2025",
    "date": "2025-01-15",
    "category": "Tax Basics",
    "readTime": "8 min read"
  },
  {
    "slug": "cryptocurrency-taxation-in-switzerland-2025",
    "title": "Cryptocurrency Taxation in Switzerland: Complete Guide 2025",
    "date": "2025-01-12",
    "category": "Digital Assets",
    "readTime": "15 min read"
  },
  {
    "slug": "expat-guide-to-pillar-3a-pension-in-switzerland-2025",
    "title": "Complete Guide to Pillar 3a Pension for Expats in Switzerland",
    "date": "2025-01-10",
    "category": "Pension & Savings",
    "readTime": "10 min read"
  },
  {
    "slug": "swiss-wealth-tax-complete-guide-2025",
    "title": "Swiss Wealth Tax: Complete Guide for Expats 2025",
    "date": "2025-01-08",
    "category": "Wealth Tax",
    "readTime": "9 min read"
  },
  {
    "slug": "navigating-swiss-real-estate-tax-for-expats-2025",
    "title": "Navigating Swiss Real Estate Tax for Expats in 2025",
    "date": "2025-01-05",
    "category": "Real Estate",
    "readTime": "12 min read"
  },
  {
    "slug": "expat-tax-planning-strategies-switzerland-2025",
    "title": "Expat Tax Planning Strategies for Switzerland 2025",
    "date": "2025-01-03",
    "category": "Tax Planning",
    "readTime": "11 min read"
  },
  {
    "slug": "swiss-business-tax-guide-for-expats-2025",
    "title": "Swiss Business Tax Guide for Expats: Starting a Business in 2025",
    "date": "2025-01-01",
    "category": "Business Tax",
    "readTime": "13 min read"
  },
  {
    "slug": "swiss-inheritance-tax-guide-2025",
    "title": "Swiss Inheritance Tax: Complete Guide for Expats 2025",
    "date": "2024-12-28",
    "category": "Estate Planning",
    "readTime": "10 min read"
  },
  {
    "slug": "swiss-health-insurance-tax-deductions-2025",
    "title": "Swiss Health Insurance Tax Deductions: Maximize Your Savings 2025",
    "date": "2024-12-25",
    "category": "Health & Insurance",
    "readTime": "7 min read"
  },
  {
    "slug": "swiss-education-tax-benefits-expats-2025",
    "title": "Swiss Education Tax Benefits for Expats: Save on School Fees 2025",
    "date": "2024-12-22",
    "category": "Education",
    "readTime": "8 min read"
  }
]
